prometheus_couchbase_exporter/__init__.py
prometheus_couchbase_exporter-1.0.3.dist-info/DESCRIPTION.rst
prometheus_couchbase_exporter-1.0.3.dist-info/METADATA
prometheus_couchbase_exporter-1.0.3.dist-info/RECORD
prometheus_couchbase_exporter-1.0.3.dist-info/WHEEL
prometheus_couchbase_exporter-1.0.3.dist-info/entry_points.txt
prometheus_couchbase_exporter-1.0.3.dist-info/metadata.json
prometheus_couchbase_exporter-1.0.3.dist-info/top_level.txt
